[
  {
    "name": "Faculty of Arts and Education",
    "URL": "https://www.deakin.edu.au/faculty-of-arts-and-education"
  },
  {
    "name": "Faculty of Business and Law",
    "URL": "https://www.deakin.edu.au/faculty-of-business-and-law"
  },
  {
    "name": "Faculty of Health",
    "URL": "https://www.deakin.edu.au/faculty-of-health"
  },
  {
    "name": "Faculty of Science, Engineering and Built Environment",
    "URL": "https://www.deakin.edu.au/about-deakin/faculties-and-schools/science-engineering-and-built-environment"
  }
]