[
  {
    "name": "Biomedical Engineering",
    "URL": "https://www.auegov.ac.in/Department/biomed"
  },
  {
    "name": "Civil Engineering",
    "URL": "https://www.auegov.ac.in/Department/civil"
  },
  {
    "name": "Chemistry",
    "URL": "https://www.auegov.ac.in/Department/chem"
  },
  {
    "name": "Computer Science and Engineering",
    "URL": "https://www.auegov.ac.in/Department/cse"
  },
  {
    "name": "Electrical and Electronics Engineering",
    "URL": "https://www.auegov.ac.in/Department/eee"
  },
  {
    "name": "Electronics and Communication Engineering",
    "URL": "https://www.auegov.ac.in/Department/ece"
  },
  {
    "name": "English",
    "URL": "https://www.auegov.ac.in/Department/english"
  },
  {
    "name": "Geology",
    "URL": "https://www.auegov.ac.in/Department/geology"
  },
  {
    "name": "Information Science and Technology",
    "URL": "https://www.auegov.ac.in/Department/ist"
  },
  {
    "name": "Industrial Engineering",
    "URL": "https://www.auegov.ac.in/Department/indus"
  },
  {
    "name": "Mathematics",
    "URL": "https://www.auegov.ac.in/Department/maths"
  },
  {
    "name": "Manufacturing Engineering",
    "URL": "https://www.auegov.ac.in/Department/manuf"
  },
  {
    "name": "Management Studies",
    "URL": "https://www.auegov.ac.in/Department/mgmt"
  },
  {
    "name": "Mechanical Engineering",
    "URL": "https://www.auegov.ac.in/Department/mech"
  },
  {
    "name": "Media Sciences",
    "URL": "https://www.auegov.ac.in/Department/media"
  },
  {
    "name": "Medical Physics",
    "URL": "https://www.auegov.ac.in/Department/medphy"
  },
  {
    "name": "Mining Engineering",
    "URL": "https://www.auegov.ac.in/Department/mining"
  },
  {
    "name": "Physics",
    "URL": "https://www.auegov.ac.in/Department/physics"
  },
  {
    "name": "Printing and Packaging Technology",
    "URL": "https://www.auegov.ac.in/Department/print"
  },
  {
    "name": "Aerospace Engineering",
    "URL": "https://www.auegov.ac.in/Department/aerospace"
  },
  {
    "name": "Automobile Engineering",
    "URL": "https://www.auegov.ac.in/Department/auto"
  },
  {
    "name": "Applied Science and Humanities",
    "URL": "https://www.auegov.ac.in/Department/ash"
  },
  {
    "name": "Computer Technology",
    "URL": "https://www.auegov.ac.in/Department/ct"
  },
  {
    "name": "Electronics Engineering",
    "URL": "https://www.auegov.ac.in/Department/elect"
  },
  {
    "name": "Information Technology",
    "URL": "https://www.auegov.ac.in/Department/it"
  },
  {
    "name": "Instrumentation Engineering",
    "URL": "https://www.auegov.ac.in/Department/instru"
  },
  {
    "name": "Production Technology",
    "URL": "https://www.auegov.ac.in/Department/prod"
  },
  {
    "name": "Rubber and Plastic Technology",
    "URL": "https://www.auegov.ac.in/Department/rpt"
  },
  {
    "name": "Applied Science Technology",
    "URL": "https://www.auegov.ac.in/Department/applied"
  },
  {
    "name": "Bio-Technology",
    "URL": "http://www.biotechannauniv.com/"
  },
  {
    "name": "Ceramic Technology",
    "URL": "https://www.auegov.ac.in/Department/cera"
  },
  {
    "name": "Chemical Engineering",
    "URL": "https://www.auegov.ac.in/Department/chemical"
  },
  {
    "name": "Leather Technology",
    "URL": "https://www.auegov.ac.in/Department/leather"
  },
  {
    "name": "Textile Technology",
    "URL": "https://www.auegov.ac.in/Department/text"
  },
  {
    "name": "Architecture",
    "URL": "https://www.auegov.ac.in/Department/arch"
  },
  {
    "name": "Planning",
    "URL": "https://www.auegov.ac.in/Department/planning"
  }
]